[
    {
      "roomName": "Standard Room 101",
      "roomNumber": "101",
      "maxCount": 2,
      "imageUrls": [],
      "currentBookings": [],
      "rentPerDay": 100,
      "floor": "ObjectId_of_floor_1",
      "roomType": "ObjectId_of_roomType_standard",
      "services": ["food", "bath"],
      "utilities": ["soap", "shampoo", "towels"],
      "ownerName": "Hotel Management",
      "status": "vacant",
      "roomDescription": "A cozy standard room with essential amenities."
    },
    {
      "roomName": "Deluxe Room 201",
      "roomNumber": "201",
      "maxCount": 4,
      "imageUrls": [],
      "currentBookings": [],
      "rentPerDay": 200,
      "floor": "ObjectId_of_floor_2",
      "roomType": "ObjectId_of_roomType_deluxe",
      "services": ["food", "bath", "snacks", "drinks"],
      "utilities": ["soap", "shampoo", "towels"],
      "ownerName": "Hotel Management",
      "status": "vacant",
      "roomDescription": "Spacious deluxe room with additional amenities."
    },
    {
      "roomName": "Family Suite 301",
      "roomNumber": "301",
      "maxCount": 6,
      "imageUrls": [],
      "currentBookings": [],
      "rentPerDay": 300,
      "floor": "ObjectId_of_floor_3",
      "roomType": "ObjectId_of_roomType_suite",
      "services": ["food", "bath", "snacks", "drinks"],
      "utilities": ["soap", "shampoo", "towels", "robe"],
      "ownerName": "Hotel Management",
      "status": "vacant",
      "roomDescription": "Luxurious family suite with ample space and premium amenities."
    },
    {
      "roomName": "Economy Room 102",
      "roomNumber": "102",
      "maxCount": 2,
      "imageUrls": [],
      "currentBookings": [],
      "rentPerDay": 80,
      "floor": "ObjectId_of_floor_1",
      "roomType": "ObjectId_of_roomType_economy",
      "services": ["bath"],
      "utilities": ["soap"],
      "ownerName": "Hotel Management",
      "status": "vacant",
      "roomDescription": "Budget-friendly economy room suitable for short stays."
    },
    {
      "roomName": "Executive Suite 401",
      "roomNumber": "401",
      "maxCount": 4,
      "imageUrls": [],
      "currentBookings": [],
      "rentPerDay": 400,
      "floor": "ObjectId_of_floor_4",
      "roomType": "ObjectId_of_roomType_suite",
      "services": ["food", "bath", "snacks", "drinks"],
      "utilities": ["soap", "shampoo", "towels", "robe"],
      "ownerName": "Hotel Management",
      "status": "vacant",
      "roomDescription": "Exclusive executive suite with premium amenities and services."
    },
    {
      "roomName": "Standard Room 801",
      "roomNumber": "801",
      "maxCount": 2,
      "imageUrls": [],
      "currentBookings": [],
      "rentPerDay": 100,
      "floor": "ObjectId_of_floor_1",
      "roomType": "ObjectId_of_roomType_standard",
      "services": ["food", "bath"],
      "utilities": ["soap", "shampoo", "towels"],
      "ownerName": "Hotel Management",
      "status": "vacant",
      "roomDescription": "A cozy standard room with essential amenities."
    },
    {
      "roomName": "Standard Room 901",
      "roomNumber": "901",
      "maxCount": 2,
      "imageUrls": [],
      "currentBookings": [],
      "rentPerDay": 100,
      "floor": "ObjectId_of_floor_1",
      "roomType": "ObjectId_of_roomType_standard",
      "services": ["food", "bath"],
      "utilities": ["soap", "shampoo", "towels"],
      "ownerName": "Hotel Management",
      "status": "vacant",
      "roomDescription": "A cozy standard room with essential amenities."
    }
  ]
  